itk/AnisotropicDiffusionLBRPython.py
itk/_AnisotropicDiffusionLBRPython.so
itk/itkAnisotropicDiffusionLBRImageFilterPython.py
itk/itkCoherenceEnhancingDiffusionImageFilterPython.py
itk/Configuration/AnisotropicDiffusionLBRConfig.py
itk/Configuration/AnisotropicDiffusionLBR_snake_case.py
itk_anisotropicdiffusionlbr-1.2.1.dist-info/LICENSE
itk_anisotropicdiffusionlbr-1.2.1.dist-info/METADATA
itk_anisotropicdiffusionlbr-1.2.1.dist-info/WHEEL
itk_anisotropicdiffusionlbr-1.2.1.dist-info/top_level.txt
itk_anisotropicdiffusionlbr-1.2.1.dist-info/RECORD
