Metadata-Version: 2.1
Name: itk-anisotropicdiffusionlbr
Version: 1.2.1
Summary: Smooth images while preserving edges or coherent structures.
Home-page: https://itk.org/
Author: Insight Software Consortium
Author-email: community@itk.org
License: Apache
Download-URL: https://github.com/InsightSoftwareConsortium/ITKAnisotropicDiffusionLBR
Keywords: ITK InsightToolkit
Platform: UNKNOWN
Classifier: License :: OSI Approved :: Apache Software License
Classifier: Programming Language :: Python
Classifier: Programming Language :: C++
Classifier: Development Status :: 4 - Beta
Classifier: Intended Audience :: Developers
Classifier: Intended Audience :: Education
Classifier: Intended Audience :: Healthcare Industry
Classifier: Intended Audience :: Science/Research
Classifier: Topic :: Scientific/Engineering
Classifier: Topic :: Scientific/Engineering :: Medical Science Apps.
Classifier: Topic :: Scientific/Engineering :: Information Analysis
Classifier: Topic :: Software Development :: Libraries
Classifier: Operating System :: Android
Classifier: Operating System :: Microsoft :: Windows
Classifier: Operating System :: POSIX
Classifier: Operating System :: Unix
Classifier: Operating System :: MacOS
Requires-Dist: itk (>=5.2.0.post2)
